{
  "cycle": 37,
  "timestamp": "2025-12-28T10:53:35.140501",
  "paper_mode": true,
  "components": {
    "live_data": "OK",
    "research_swarm": "DISPATCHED",
    "agent_council": "OK"
  },
  "signals": {
    "BTC": {
      "symbol": "BTC",
      "regime": "Low Volatility Trend",
      "direction": "SHORT",
      "confidence": 50,
      "entry_price": 87551.16,
      "stop_loss": 90177.69480000001,
      "take_profit": 83173.602,
      "position_size": 25.0,
      "reasoning": "BTC in Low Volatility Trend regime. Profile: Sniper Scalp. 24h change: 0.0%. ADX: 39.8. Recommended: SHORT with 50% confidence.",
      "sources": [
        "Coinbase/CCXT",
        "StrategyEngine"
      ],
      "timestamp": "2025-12-28T10:53:41.420768"
    },
    "ETH": {
      "symbol": "ETH",
      "regime": "Transitioning Market",
      "direction": "NEUTRAL",
      "confidence": 30,
      "entry_price": 2930.69,
      "stop_loss": 2842.7693,
      "take_profit": 3077.2245000000003,
      "position_size": 15.0,
      "reasoning": "ETH in Transitioning Market regime. Profile: Sniper Scalp. 24h change: 0.0%. ADX: 21.5. Recommended: NEUTRAL with 30% confidence.",
      "sources": [
        "Coinbase/CCXT",
        "StrategyEngine"
      ],
      "timestamp": "2025-12-28T10:53:41.624440"
    },
    "SOL": {
      "symbol": "SOL",
      "regime": "Transitioning Market",
      "direction": "NEUTRAL",
      "confidence": 30,
      "entry_price": 123.3,
      "stop_loss": 104.80499999999999,
      "take_profit": 160.29,
      "position_size": 15.0,
      "reasoning": "SOL in Transitioning Market regime. Profile: Swing Trade. 24h change: 0.0%. ADX: 23.5. Recommended: NEUTRAL with 30% confidence.",
      "sources": [
        "Coinbase/CCXT",
        "StrategyEngine"
      ],
      "timestamp": "2025-12-28T10:53:41.907690"
    },
    "XRP": {
      "symbol": "XRP",
      "regime": "Low Volatility Trend",
      "direction": "SHORT",
      "confidence": 50,
      "entry_price": 1.8567,
      "stop_loss": 2.135205,
      "take_profit": 1.29969,
      "position_size": 25.0,
      "reasoning": "XRP in Low Volatility Trend regime. Profile: Swing Trade. 24h change: 0.0%. ADX: 38.9. Recommended: SHORT with 50% confidence.",
      "sources": [
        "Coinbase/CCXT",
        "StrategyEngine"
      ],
      "timestamp": "2025-12-28T10:53:42.145768"
    },
    "AAVE": {
      "symbol": "AAVE",
      "regime": "Low Volatility Trend",
      "direction": "SHORT",
      "confidence": 50,
      "entry_price": 153.58,
      "stop_loss": 176.617,
      "take_profit": 107.506,
      "position_size": 25.0,
      "reasoning": "AAVE in Low Volatility Trend regime. Profile: Swing Trade. 24h change: 0.0%. ADX: 30.8. Recommended: SHORT with 50% confidence.",
      "sources": [
        "Coinbase/CCXT",
        "StrategyEngine"
      ],
      "timestamp": "2025-12-28T10:53:42.439723"
    },
    "ADA": {
      "symbol": "ADA",
      "regime": "Transitioning Market",
      "direction": "NEUTRAL",
      "confidence": 30,
      "entry_price": 0.3638,
      "stop_loss": 0.30923,
      "take_profit": 0.47294,
      "position_size": 15.0,
      "reasoning": "ADA in Transitioning Market regime. Profile: Swing Trade. 24h change: 0.0%. ADX: 54.7. Recommended: NEUTRAL with 30% confidence.",
      "sources": [
        "Coinbase/CCXT",
        "StrategyEngine"
      ],
      "timestamp": "2025-12-28T10:53:42.844442"
    },
    "AVAX": {
      "symbol": "AVAX",
      "regime": "Low Volatility Trend",
      "direction": "SHORT",
      "confidence": 50,
      "entry_price": 12.6,
      "stop_loss": 14.489999999999998,
      "take_profit": 8.819999999999999,
      "position_size": 25.0,
      "reasoning": "AVAX in Low Volatility Trend regime. Profile: Swing Trade. 24h change: 0.0%. ADX: 45.6. Recommended: SHORT with 50% confidence.",
      "sources": [
        "Coinbase/CCXT",
        "StrategyEngine"
      ],
      "timestamp": "2025-12-28T10:53:43.145566"
    },
    "DOT": {
      "symbol": "DOT",
      "regime": "Low Volatility Trend",
      "direction": "SHORT",
      "confidence": 50,
      "entry_price": 1.852,
      "stop_loss": 2.1298,
      "take_profit": 1.2964,
      "position_size": 25.0,
      "reasoning": "DOT in Low Volatility Trend regime. Profile: Swing Trade. 24h change: 0.0%. ADX: 37.2. Recommended: SHORT with 50% confidence.",
      "sources": [
        "Coinbase/CCXT",
        "StrategyEngine"
      ],
      "timestamp": "2025-12-28T10:53:43.491901"
    },
    "ATOM": {
      "symbol": "ATOM",
      "regime": "Low Volatility Trend",
      "direction": "SHORT",
      "confidence": 50,
      "entry_price": 2.068,
      "stop_loss": 2.3782,
      "take_profit": 1.4476,
      "position_size": 25.0,
      "reasoning": "ATOM in Low Volatility Trend regime. Profile: Swing Trade. 24h change: 0.0%. ADX: 41.1. Recommended: SHORT with 50% confidence.",
      "sources": [
        "Coinbase/CCXT",
        "StrategyEngine"
      ],
      "timestamp": "2025-12-28T10:53:43.696834"
    },
    "NEAR": {
      "symbol": "NEAR",
      "regime": "Low Volatility Trend",
      "direction": "SHORT",
      "confidence": 50,
      "entry_price": 1.561,
      "stop_loss": 1.7951499999999998,
      "take_profit": 1.0926999999999998,
      "position_size": 25.0,
      "reasoning": "NEAR in Low Volatility Trend regime. Profile: Swing Trade. 24h change: 0.0%. ADX: 48.5. Recommended: SHORT with 50% confidence.",
      "sources": [
        "Coinbase/CCXT",
        "StrategyEngine"
      ],
      "timestamp": "2025-12-28T10:53:44.055965"
    },
    "APT": {
      "symbol": "APT",
      "regime": "Low Volatility Trend",
      "direction": "SHORT",
      "confidence": 50,
      "entry_price": 1.7099,
      "stop_loss": 1.9663849999999998,
      "take_profit": 1.1969299999999998,
      "position_size": 25.0,
      "reasoning": "APT in Low Volatility Trend regime. Profile: Swing Trade. 24h change: 0.0%. ADX: 27.7. Recommended: SHORT with 50% confidence.",
      "sources": [
        "Coinbase/CCXT",
        "StrategyEngine"
      ],
      "timestamp": "2025-12-28T10:53:44.407551"
    },
    "SUI": {
      "symbol": "SUI",
      "regime": "Low Volatility Trend",
      "direction": "SHORT",
      "confidence": 50,
      "entry_price": 1.4437,
      "stop_loss": 1.6602549999999998,
      "take_profit": 1.0105899999999999,
      "position_size": 25.0,
      "reasoning": "SUI in Low Volatility Trend regime. Profile: Swing Trade. 24h change: 0.0%. ADX: 48.7. Recommended: SHORT with 50% confidence.",
      "sources": [
        "Coinbase/CCXT",
        "StrategyEngine"
      ],
      "timestamp": "2025-12-28T10:53:44.741517"
    },
    "MATIC": {
      "symbol": "MATIC",
      "regime": "Unknown",
      "direction": "NEUTRAL",
      "confidence": 0,
      "entry_price": 0,
      "stop_loss": 0,
      "take_profit": 0,
      "position_size": 0,
      "reasoning": "No price data available",
      "sources": [],
      "timestamp": "2025-12-28T10:53:44.741594"
    },
    "ARB": {
      "symbol": "ARB",
      "regime": "Low Volatility Trend",
      "direction": "SHORT",
      "confidence": 50,
      "entry_price": 0.1937,
      "stop_loss": 0.222755,
      "take_profit": 0.13559,
      "position_size": 25.0,
      "reasoning": "ARB in Low Volatility Trend regime. Profile: Swing Trade. 24h change: 0.0%. ADX: 40.1. Recommended: SHORT with 50% confidence.",
      "sources": [
        "Coinbase/CCXT",
        "StrategyEngine"
      ],
      "timestamp": "2025-12-28T10:53:45.099954"
    },
    "OP": {
      "symbol": "OP",
      "regime": "Transitioning Market",
      "direction": "NEUTRAL",
      "confidence": 30,
      "entry_price": 0.272,
      "stop_loss": 0.23120000000000002,
      "take_profit": 0.3536,
      "position_size": 15.0,
      "reasoning": "OP in Transitioning Market regime. Profile: Swing Trade. 24h change: 0.0%. ADX: 23.5. Recommended: NEUTRAL with 30% confidence.",
      "sources": [
        "Coinbase/CCXT",
        "StrategyEngine"
      ],
      "timestamp": "2025-12-28T10:53:45.457589"
    },
    "UNI": {
      "symbol": "UNI",
      "regime": "High Volatility Trend",
      "direction": "SHORT",
      "confidence": 50,
      "entry_price": 6.176,
      "stop_loss": 7.102399999999999,
      "take_profit": 4.3232,
      "position_size": 25.0,
      "reasoning": "UNI in High Volatility Trend regime. Profile: Swing Trade. 24h change: 0.0%. ADX: 66.0. Recommended: SHORT with 50% confidence.",
      "sources": [
        "Coinbase/CCXT",
        "StrategyEngine"
      ],
      "timestamp": "2025-12-28T10:53:45.800364"
    },
    "LINK": {
      "symbol": "LINK",
      "regime": "Transitioning Market",
      "direction": "NEUTRAL",
      "confidence": 30,
      "entry_price": 12.359,
      "stop_loss": 10.50515,
      "take_profit": 16.0667,
      "position_size": 15.0,
      "reasoning": "LINK in Transitioning Market regime. Profile: Swing Trade. 24h change: 0.0%. ADX: 21.4. Recommended: NEUTRAL with 30% confidence.",
      "sources": [
        "Coinbase/CCXT",
        "StrategyEngine"
      ],
      "timestamp": "2025-12-28T10:53:46.183345"
    },
    "MKR": {
      "symbol": "MKR",
      "regime": "Transitioning Market",
      "direction": "NEUTRAL",
      "confidence": 30,
      "entry_price": 1492.49,
      "stop_loss": 1268.6165,
      "take_profit": 1940.237,
      "position_size": 15.0,
      "reasoning": "MKR in Transitioning Market regime. Profile: Swing Trade. 24h change: 0.0%. ADX: 31.2. Recommended: NEUTRAL with 30% confidence.",
      "sources": [
        "Coinbase/CCXT",
        "StrategyEngine"
      ],
      "timestamp": "2025-12-28T10:53:46.413930"
    },
    "CRV": {
      "symbol": "CRV",
      "regime": "Low Volatility Trend",
      "direction": "SHORT",
      "confidence": 50,
      "entry_price": 0.3902,
      "stop_loss": 0.44872999999999996,
      "take_profit": 0.27314,
      "position_size": 25.0,
      "reasoning": "CRV in Low Volatility Trend regime. Profile: Swing Trade. 24h change: 0.0%. ADX: 38.0. Recommended: SHORT with 50% confidence.",
      "sources": [
        "Coinbase/CCXT",
        "StrategyEngine"
      ],
      "timestamp": "2025-12-28T10:53:46.817624"
    },
    "LDO": {
      "symbol": "LDO",
      "regime": "Transitioning Market",
      "direction": "NEUTRAL",
      "confidence": 30,
      "entry_price": 0.578,
      "stop_loss": 0.49129999999999996,
      "take_profit": 0.7514,
      "position_size": 15.0,
      "reasoning": "LDO in Transitioning Market regime. Profile: Swing Trade. 24h change: 0.0%. ADX: 71.3. Recommended: NEUTRAL with 30% confidence.",
      "sources": [
        "Coinbase/CCXT",
        "StrategyEngine"
      ],
      "timestamp": "2025-12-28T10:53:47.163768"
    },
    "DOGE": {
      "symbol": "DOGE",
      "regime": "Low Volatility Trend",
      "direction": "SHORT",
      "confidence": 50,
      "entry_price": 0.12342,
      "stop_loss": 0.14810399999999999,
      "take_profit": 0.06171,
      "position_size": 18.35,
      "reasoning": "DOGE in Low Volatility Trend regime. Profile: Meme Hunter. 24h change: 0.0%. ADX: 30.2. Recommended: SHORT with 50% confidence.",
      "sources": [
        "Coinbase/CCXT",
        "StrategyEngine"
      ],
      "timestamp": "2025-12-28T10:53:47.420563"
    },
    "SHIB": {
      "symbol": "SHIB",
      "regime": "Low Volatility Trend",
      "direction": "SHORT",
      "confidence": 50,
      "entry_price": 7.28e-06,
      "stop_loss": 8.735999999999999e-06,
      "take_profit": 3.64e-06,
      "position_size": 18.35,
      "reasoning": "SHIB in Low Volatility Trend regime. Profile: Meme Hunter. 24h change: 0.0%. ADX: 27.9. Recommended: SHORT with 50% confidence.",
      "sources": [
        "Coinbase/CCXT",
        "StrategyEngine"
      ],
      "timestamp": "2025-12-28T10:53:47.866491"
    },
    "PEPE": {
      "symbol": "PEPE",
      "regime": "Transitioning Market",
      "direction": "NEUTRAL",
      "confidence": 30,
      "entry_price": 4.14e-06,
      "stop_loss": 3.3120000000000002e-06,
      "take_profit": 6.21e-06,
      "position_size": 11.01,
      "reasoning": "PEPE in Transitioning Market regime. Profile: Meme Hunter. 24h change: 0.0%. ADX: 30.3. Recommended: NEUTRAL with 30% confidence.",
      "sources": [
        "Coinbase/CCXT",
        "StrategyEngine"
      ],
      "timestamp": "2025-12-28T10:53:48.057390"
    },
    "FET": {
      "symbol": "FET",
      "regime": "Transitioning Market",
      "direction": "NEUTRAL",
      "confidence": 30,
      "entry_price": 0.2139,
      "stop_loss": 0.181815,
      "take_profit": 0.27807000000000004,
      "position_size": 15.0,
      "reasoning": "FET in Transitioning Market regime. Profile: Swing Trade. 24h change: 0.0%. ADX: 30.1. Recommended: NEUTRAL with 30% confidence.",
      "sources": [
        "Coinbase/CCXT",
        "StrategyEngine"
      ],
      "timestamp": "2025-12-28T10:53:48.394024"
    },
    "RNDR": {
      "symbol": "RNDR",
      "regime": "Unknown",
      "direction": "NEUTRAL",
      "confidence": 30,
      "entry_price": 2.9685,
      "stop_loss": 2.523225,
      "take_profit": 3.8590500000000003,
      "position_size": 15.0,
      "reasoning": "RNDR in Unknown regime. Profile: Swing Trade. 24h change: 0.0%. ADX: 0.0. Recommended: NEUTRAL with 30% confidence.",
      "sources": [
        "Coinbase/CCXT",
        "StrategyEngine"
      ],
      "timestamp": "2025-12-28T10:53:48.559759"
    },
    "TAO": {
      "symbol": "TAO",
      "regime": "Low Volatility Trend",
      "direction": "SHORT",
      "confidence": 50,
      "entry_price": 221.96,
      "stop_loss": 255.254,
      "take_profit": 155.37199999999999,
      "position_size": 25.0,
      "reasoning": "TAO in Low Volatility Trend regime. Profile: Swing Trade. 24h change: 0.0%. ADX: 36.6. Recommended: SHORT with 50% confidence.",
      "sources": [
        "Coinbase/CCXT",
        "StrategyEngine"
      ],
      "timestamp": "2025-12-28T10:53:48.920276"
    }
  },
  "opportunities": [],
  "summary": {
    "long": [],
    "short": [
      "BTC",
      "XRP",
      "AAVE",
      "AVAX",
      "DOT",
      "ATOM",
      "NEAR",
      "APT",
      "SUI",
      "ARB",
      "UNI",
      "CRV",
      "DOGE",
      "SHIB",
      "TAO"
    ],
    "neutral": [
      "ETH",
      "SOL",
      "ADA",
      "MATIC",
      "OP",
      "LINK",
      "MKR",
      "LDO",
      "PEPE",
      "FET",
      "RNDR"
    ]
  },
  "manus_task": null,
  "council_opinion": {
    "recommendation": "HOLD",
    "confidence": 50,
    "agents": {
      "reflect": {
        "signal": "NEUTRAL",
        "confidence": 50,
        "reasoning": "reflect analysis pending - needs market data",
        "agent": "reflect"
      },
      "risk": {
        "signal": "NEUTRAL",
        "confidence": 50,
        "reasoning": "risk analysis pending - needs market data",
        "agent": "risk"
      },
      "portfolio": {
        "signal": "NEUTRAL",
        "confidence": 50,
        "reasoning": "portfolio analysis pending - needs market data",
        "agent": "portfolio"
      }
    },
    "signal_counts": {
      "BUY": 0,
      "SELL": 0,
      "HOLD": 0,
      "NEUTRAL": 3
    },
    "reasoning": "Council voted: BUY=0, SELL=0, HOLD=0",
    "timestamp": "2025-12-28T10:59:07.375070"
  }
}